rstructs/__init__.py
rstructs/reactive_dict.py
rstructs/reactive_list.py
rstructs/reactive_struct.py
rstructs-1.0.0.dist-info/WHEEL
rstructs-1.0.0.dist-info/METADATA
rstructs-1.0.0.dist-info/RECORD
