Metadata-Version: 2.1
Name: rstructs
Version: 1.0.0
Summary: Reactive structures - data structures with events.
Keywords: reactive,structures,classes,list,dict,event,callback
Author-email: baterflyrity <baterflyrity@yandex.ru>
Classifier: Operating System :: OS Independent
Requires-Dist: eventsystem >=1.0.0
Project-URL: Bugtracker, https://github.com/baterflyrity/rstructs/issues
Project-URL: Home, https://pypi.org/project/rstructs
Project-URL: Sources, https://github.com/baterflyrity/rstructs
